bqapi/__init__.py
bqapi/blockable_module.py
bqapi/bqclass.py
bqapi/bqfeature.py
bqapi/casauth.py
bqapi/comm.py
bqapi/exception.py
bqapi/services.py
bqapi/util.py
bqapi/xmldict.py
bqapi/RequestsMonkeyPatch/__init__.py
bqapi/RequestsMonkeyPatch/monkeypatch.py
bqapi/RequestsMonkeyPatch/requests_patch.py
bqapi/tests/__init__.py
bqapi/tests/conftest.py
bqapi/tests/test_bqapi.py
bqapi/tests/test_bqclass.py
bqapi/tests/test_bqfeature.py
bqapi/tests/test_comm.py
bqapi/tests/test_util.py
bqapi/tests/util.py
bqapi_ucsb-1.0.7.dist-info/licenses/LICENSE.txt
bqapi_ucsb-1.0.7.dist-info/METADATA
bqapi_ucsb-1.0.7.dist-info/WHEEL
bqapi_ucsb-1.0.7.dist-info/top_level.txt
bqapi_ucsb-1.0.7.dist-info/RECORD
